<annotation>
	<folder></folder>
	<filename>1599890_jpg.rf.7be5b8b716f2a5ffa4a3e32841d2ae83.jpg</filename>
	<path>1599890_jpg.rf.7be5b8b716f2a5ffa4a3e32841d2ae83.jpg</path>
	<source>
		<database>roboflow.com</database>
	</source>
	<size>
		<width>800</width>
		<height>533</height>
		<depth>3</depth>
	</size>
	<segmented>0</segmented>
	<object>
		<name>fall-armyworm</name>
		<pose>Unspecified</pose>
		<truncated>0</truncated>
		<difficult>0</difficult>
		<occluded>0</occluded>
		<bndbox>
			<xmin>286</xmin>
			<xmax>682</xmax>
			<ymin>71</ymin>
			<ymax>427</ymax>
		</bndbox>
		<polygon>
			<x1>582.96875</x1>
			<y1>153.029297</y1>
			<x2>453.882812</x2>
			<y2>244.638672</y2>
			<x3>357.068359</x3>
			<y3>330.001953</y3>
			<x4>312.304688</x4>
			<y4>378.929688</y4>
			<x5>289.402344</x5>
			<y5>396.626953</y5>
			<x6>285.238281</x6>
			<y6>405.996094</y6>
			<x7>290.443359</x7>
			<y7>416.40625</y7>
			<x8>306.058594</x8>
			<y8>425.775391</y8>
			<x9>332.083984</x9>
			<y9>415.365234</y9>
			<x10>494.482422</x10>
			<y10>283.15625</y10>
			<x11>563.189453</x11>
			<y11>238.392578</y11>
			<x12>641.265625</x12>
			<y12>171.767578</y12>
			<x13>680.824219</x13>
			<y13>93.691406</y13>
			<x14>677.701172</x14>
			<y14>73.912109</y14>
			<x15>656.880859</x15>
			<y15>69.748047</y15>
			<x16>647.511719</x16>
			<y16>71.830078</y16>
			<x17>625.650391</x17>
			<y17>88.486328</y17>
			<x18>582.96875</x18>
			<y18>153.029297</y18>
		</polygon>
	</object>
</annotation>
