<annotation>
	<folder></folder>
	<filename>Fall-armyworm-update-F01_jpg.rf.1af42c85d5f1096fb06ad9bd58e6bd43.jpg</filename>
	<path>Fall-armyworm-update-F01_jpg.rf.1af42c85d5f1096fb06ad9bd58e6bd43.jpg</path>
	<source>
		<database>roboflow.com</database>
	</source>
	<size>
		<width>800</width>
		<height>533</height>
		<depth>3</depth>
	</size>
	<segmented>0</segmented>
	<object>
		<name>fall-armyworm</name>
		<pose>Unspecified</pose>
		<truncated>0</truncated>
		<difficult>0</difficult>
		<occluded>0</occluded>
		<bndbox>
			<xmin>193</xmin>
			<xmax>533</xmax>
			<ymin>10</ymin>
			<ymax>534</ymax>
		</bndbox>
		<polygon>
			<x1>382.96669</x1>
			<y1>533</y1>
			<x2>428.124507</x2>
			<y2>480.381031</y2>
			<x3>472.847778</x3>
			<y3>404.68146</y3>
			<x4>498.765418</x4>
			<y4>347.461121</y4>
			<x5>522.559967</x5>
			<y5>267.933438</y5>
			<x6>532.091892</x6>
			<y6>195.470703</y6>
			<x7>528.925223</x7>
			<y7>128.399754</y7>
			<x8>514.959425</x8>
			<y8>79.435731</y8>
			<x9>483.379318</x9>
			<y9>31.290777</y9>
			<x10>461.283269</x10>
			<y10>10.736487</y10>
			<x11>390.693613</x11>
			<y11>9.093495</y11>
			<x12>209.012114</x12>
			<y12>17.541705</y12>
			<x13>208.785193</x13>
			<y13>19.72615</y13>
			<x14>191.644403</x14>
			<y14>32.053015</y14>
			<x15>195.368794</x15>
			<y15>54.285897</y15>
			<x16>216.315758</x16>
			<y16>51.021665</y16>
			<x17>249.915748</x17>
			<y17>56.236665</y17>
			<x18>256.441234</x18>
			<y18>67.390233</y18>
			<x19>274.854654</x19>
			<y19>70.419927</y19>
			<x20>284.214867</x20>
			<y20>76.606839</y20>
			<x21>310.971284</x21>
			<y21>82.109531</y21>
			<x22>328.798</x22>
			<y22>90.355489</y22>
			<x23>357.050869</x23>
			<y23>91.27271</y23>
			<x24>363.0222</x24>
			<y24>94.502996</y24>
			<x25>389.052991</x25>
			<y25>110.897327</y25>
			<x26>395.052153</x26>
			<y26>114.262859</y26>
			<x27>400.653755</x27>
			<y27>135.932316</y27>
			<x28>405.923225</x28>
			<y28>146.922827</y28>
			<x29>403.876015</x29>
			<y29>196.631455</y29>
			<x30>413.113984</x30>
			<y30>214.553383</y30>
			<x31>398.551661</x31>
			<y31>243.291605</y31>
			<x32>397.104101</x32>
			<y32>256.648765</y32>
			<x33>398.508021</x33>
			<y33>285.926427</y33>
			<x34>391.305162</x34>
			<y34>292.111069</y34>
			<x35>383.150798</x35>
			<y35>307.816899</y35>
			<x36>374.68257</x36>
			<y36>319.621887</y36>
			<x37>374.301687</x37>
			<y37>346.505666</y37>
			<x38>359.102726</x38>
			<y38>365.450934</y38>
			<x39>344.631968</x39>
			<y39>392.664829</y39>
			<x40>315.733955</x40>
			<y40>443.584032</y40>
			<x41>298.949546</x41>
			<y41>458.05231</y41>
			<x42>290.971874</x42>
			<y42>476.652797</y42>
			<x43>243.935691</x43>
			<y43>533</y43>
			<x44>382.96669</x44>
			<y44>533</y44>
		</polygon>
	</object>
</annotation>
