<annotation>
	<folder></folder>
	<filename>fall-armyworm-fig1_jpg.rf.35c5c097298435465ba4aed34ae340f7.jpg</filename>
	<path>fall-armyworm-fig1_jpg.rf.35c5c097298435465ba4aed34ae340f7.jpg</path>
	<source>
		<database>roboflow.com</database>
	</source>
	<size>
		<width>800</width>
		<height>533</height>
		<depth>3</depth>
	</size>
	<segmented>0</segmented>
	<object>
		<name>fall-armyworm</name>
		<pose>Unspecified</pose>
		<truncated>0</truncated>
		<difficult>0</difficult>
		<occluded>0</occluded>
		<bndbox>
			<xmin>151</xmin>
			<xmax>628</xmax>
			<ymin>212</ymin>
			<ymax>345</ymax>
		</bndbox>
		<polygon>
			<x1>450.915081</x1>
			<y1>229.431918</y1>
			<x2>433.746706</x2>
			<y2>231.77306</y2>
			<x3>415.79795</x3>
			<y3>242.698389</y3>
			<x4>400.190337</x4>
			<y4>245.039531</y4>
			<x5>385.363104</x5>
			<y5>252.062958</y5>
			<x6>367.414348</x6>
			<y6>251.282577</y6>
			<x7>359.610542</x7>
			<y7>256.745242</y7>
			<x8>340.101025</x8>
			<y8>253.623719</y8>
			<x9>318.250366</x9>
			<y9>255.964861</y9>
			<x10>301.862372</x10>
			<y10>249.721816</y10>
			<x11>282.352855</x11>
			<y11>248.941435</y11>
			<x12>263.623719</x12>
			<y12>235.674963</y12>
			<x13>243.333821</x13>
			<y13>233.333821</y13>
			<x14>223.043924</x14>
			<y14>222.408492</y14>
			<x15>195.7306</x15>
			<y15>216.165447</y15>
			<x16>159.833089</x16>
			<y16>234.114202</y16>
			<x17>154.370425</x17>
			<y17>245.819912</y17>
			<x18>150.468521</x18>
			<y18>270.011713</y18>
			<x19>153.590044</x19>
			<y19>276.254758</y19>
			<x20>165.295754</x20>
			<y20>278.5959</y20>
			<x21>186.366032</x21>
			<y21>292.642753</y21>
			<x22>208.216691</x22>
			<y22>301.22694</y22>
			<x23>215.240117</x23>
			<y23>310.591508</y23>
			<x24>237.871157</x24>
			<y24>315.273792</y24>
			<x25>249.576867</x25>
			<y25>314.493411</y25>
			<x26>272.988287</x26>
			<y26>330.881406</y26>
			<x27>283.913616</x27>
			<y27>331.661786</y27>
			<x28>301.081991</x28>
			<y28>327.759883</y28>
			<x29>324.493411</x29>
			<y29>342.587116</y29>
			<x30>333.85798</x30>
			<y30>342.587116</y30>
			<x31>351.806735</x31>
			<y31>334.783309</y31>
			<x32>356.489019</x32>
			<y32>344.147877</y32>
			<x33>363.512445</x33>
			<y33>344.147877</y33>
			<x34>393.947291</x34>
			<y34>332.442167</y34>
			<x35>418.919473</x35>
			<y35>332.442167</y35>
			<x36>435.307467</x36>
			<y36>323.85798</y36>
			<x37>444.672035</x37>
			<y37>314.493411</y37>
			<x38>461.060029</x38>
			<y38>312.93265</y38>
			<x39>469.644217</x39>
			<y39>308.250366</y39>
			<x40>477.448023</x40>
			<y40>298.105417</y40>
			<x41>487.592972</x41>
			<y41>296.544656</y41>
			<x42>494.616398</x42>
			<y42>298.885798</y42>
			<x43>503.980966</x43>
			<y43>290.301611</y43>
			<x44>521.929722</x44>
			<y44>288.740849</y44>
			<x45>534.415813</x45>
			<y45>282.497804</y45>
			<x46>539.098097</x46>
			<y46>275.474378</y46>
			<x47>549.243045</x47>
			<y47>271.572474</y47>
			<x48>562.509517</x48>
			<y48>270.792094</y48>
			<x49>560.948755</x49>
			<y49>282.497804</y49>
			<x50>564.070278</x50>
			<y50>284.838946</y50>
			<x51>597.626647</x51>
			<y51>292.642753</y51>
			<x52>604.650073</x52>
			<y52>298.885798</y52>
			<x53>615.575403</x53>
			<y53>298.105417</y53>
			<x54>615.575403</x54>
			<y54>291.081991</y54>
			<x55>622.598829</x55>
			<y55>287.180088</y55>
			<x56>626.500732</x56>
			<y56>280.156662</y56>
			<x57>626.500732</x57>
			<y57>259.866764</y57>
			<x58>622.598829</x58>
			<y58>248.161054</y58>
			<x59>604.650073</x59>
			<y59>230.212299</y59>
			<x60>553.925329</x60>
			<y60>213.043924</y60>
			<x61>527.392387</x61>
			<y61>211.483163</y61>
			<x62>487.592972</x62>
			<y62>217.726208</y62>
			<x63>474.326501</x63>
			<y63>216.945827</y63>
			<x64>450.915081</x64>
			<y64>229.431918</y64>
		</polygon>
	</object>
</annotation>
